README.md
setup.py
cas_simulation/__init__.py
cas_simulation/cas_simulation.py
cas_simulation/check_cas_sp.py
cas_simulation.egg-info/PKG-INFO
cas_simulation.egg-info/SOURCES.txt
cas_simulation.egg-info/dependency_links.txt
cas_simulation.egg-info/entry_points.txt
cas_simulation.egg-info/requires.txt
cas_simulation.egg-info/top_level.txt