Metadata-Version: 2.1
Name: cas-simulation
Version: 1.0.1
Summary: Simulate an authentication workflow for CAS, particularly for service checks
Home-page: https://bitbucket.org/csusb/cas-simulation
Author: James Macdonell
Author-email: jmacdone@csusb.edu
License: UNKNOWN
Platform: UNKNOWN
